mlscore/__init__.py
mlscore/core.py
mlscore-0.1.0.dist-info/licenses/LICENSE
mlscore-0.1.0.dist-info/METADATA
mlscore-0.1.0.dist-info/WHEEL
mlscore-0.1.0.dist-info/top_level.txt
mlscore-0.1.0.dist-info/RECORD
