Metadata-Version: 2.4
Name: mlscore
Version: 0.1.0
Summary: A comprehensive machine learning evaluation metrics library
Home-page: https://github.com/sachin62025/mlscore
Author: sachin kuamr
Author-email: sachin18449kumar@gmail.com
Classifier: Programming Language :: Python :: 3
Classifier: License :: OSI Approved :: MIT License
Classifier: Operating System :: OS Independent
Requires-Python: >=3.6
License-File: LICENSE
Requires-Dist: numpy>=1.19.0
Requires-Dist: scikit-learn>=0.24.0
Dynamic: author
Dynamic: author-email
Dynamic: classifier
Dynamic: description
Dynamic: description-content-type
Dynamic: home-page
Dynamic: license-file
Dynamic: requires-dist
Dynamic: requires-python
Dynamic: summary
